kivyredux/__init__.py
kivyredux/actions.py
kivyredux/constants.py
kivyredux/error.py
kivyredux/mixins.py
kivyredux/reducers.py
kivyredux/state.py
kivyredux/store.py
kivyredux-1.1.dist-info/LICENSE
kivyredux-1.1.dist-info/METADATA
kivyredux-1.1.dist-info/WHEEL
kivyredux-1.1.dist-info/top_level.txt
kivyredux-1.1.dist-info/RECORD
