Metadata-Version: 2.1
Name: kivyredux
Version: 1.1
Summary: kivyredux - Redux for Kivy
Home-page: https://github.com/VigneshwaranJheyaraman/kivy-redux
Author: VickySuraj
Author-email: vigneshwaranjheyaraman@gmail.com
License: UNKNOWN
Keywords: python,kivy,redux,pip
Platform: UNKNOWN
Classifier: Programming Language :: Python :: 3
Classifier: License :: OSI Approved :: MIT License
Classifier: Operating System :: OS Independent
Requires-Python: >=3
Requires-Dist: Kivy (>=1.1.0)
